arneso_pypitemplate_instance/__init__.py
arneso_pypitemplate_instance/__main__.py
arneso_pypitemplate_instance/functions.py
arneso_pypitemplate_instance/py.typed
arneso_pypitemplate_instance-0.3.0.dist-info/LICENSE
arneso_pypitemplate_instance-0.3.0.dist-info/METADATA
arneso_pypitemplate_instance-0.3.0.dist-info/WHEEL
arneso_pypitemplate_instance-0.3.0.dist-info/entry_points.txt
arneso_pypitemplate_instance-0.3.0.dist-info/RECORD
