Metadata-Version: 2.3
Name: arneso-pypitemplate-instance
Version: 0.3.0
Summary: Arneso Pypitemplate Instance
License: MIT
Author: Arne Sørli
Author-email: arne.sorli@ssb.no
Maintainer: Statistics Norway, IT-partner Department (703)
Requires-Python: >=3.10,<4.0
Classifier: Development Status :: 4 - Beta
Classifier: License :: OSI Approved :: MIT License
Classifier: Programming Language :: Python :: 3
Classifier: Programming Language :: Python :: 3.10
Classifier: Programming Language :: Python :: 3.11
Classifier: Programming Language :: Python :: 3.12
Classifier: Programming Language :: Python :: 3.13
Requires-Dist: click (>=8.0.1)
Project-URL: Changelog, https://github.com/arneso-ssb/arneso-pypitemplate-instance/releases
Project-URL: Documentation, https://arneso-ssb.github.io/arneso-pypitemplate-instance
Project-URL: Homepage, https://github.com/arneso-ssb/arneso-pypitemplate-instance
Project-URL: Repository, https://github.com/arneso-ssb/arneso-pypitemplate-instance
